odoo8_addon_cron_inactivity_period-8.0.1.0.0.99.dev1-py2.7-nspkg.pth
odoo8_addon_cron_inactivity_period-8.0.1.0.0.99.dev1.dist-info/METADATA
odoo8_addon_cron_inactivity_period-8.0.1.0.0.99.dev1.dist-info/RECORD
odoo8_addon_cron_inactivity_period-8.0.1.0.0.99.dev1.dist-info/WHEEL
odoo8_addon_cron_inactivity_period-8.0.1.0.0.99.dev1.dist-info/namespace_packages.txt
odoo8_addon_cron_inactivity_period-8.0.1.0.0.99.dev1.dist-info/top_level.txt
odoo_addons/cron_inactivity_period/README.rst
odoo_addons/cron_inactivity_period/__init__.py
odoo_addons/cron_inactivity_period/__openerp__.py
odoo_addons/cron_inactivity_period/demo/res_groups.xml
odoo_addons/cron_inactivity_period/i18n/cron_inactivity_period.pot
odoo_addons/cron_inactivity_period/i18n/fr.po
odoo_addons/cron_inactivity_period/models/__init__.py
odoo_addons/cron_inactivity_period/models/ir_cron.py
odoo_addons/cron_inactivity_period/models/ir_cron_inactivity_period.py
odoo_addons/cron_inactivity_period/security/ir.model.access.csv
odoo_addons/cron_inactivity_period/static/description/icon.png
odoo_addons/cron_inactivity_period/static/description/ir_cron_form.png
odoo_addons/cron_inactivity_period/tests/__init__.py
odoo_addons/cron_inactivity_period/tests/test_module.py
odoo_addons/cron_inactivity_period/views/ir_cron.xml
